jupyterlab_wav/__init__.py
jupyterlab_wav/_version.py
jupyterlab_wav/labextension/build_log.json
jupyterlab_wav/labextension/package.json
jupyterlab_wav/labextension/static/534.ca12243b76781e1a57c5.js
jupyterlab_wav/labextension/static/796.10ba19c1daea40efab05.js
jupyterlab_wav/labextension/static/796.10ba19c1daea40efab05.js.LICENSE.txt
jupyterlab_wav/labextension/static/800.f6e75ea308f838d0a123.js
jupyterlab_wav/labextension/static/891.b9835b577fcb3308270d.js
jupyterlab_wav/labextension/static/891.b9835b577fcb3308270d.js.LICENSE.txt
jupyterlab_wav/labextension/static/lib_index_js.bbfecac10a37e1481591.js
jupyterlab_wav/labextension/static/lib_index_js.bbfecac10a37e1481591.js.map
jupyterlab_wav/labextension/static/remoteEntry.5b1700d2534d43a2b820.js
jupyterlab_wav/labextension/static/remoteEntry.5b1700d2534d43a2b820.js.map
jupyterlab_wav/labextension/static/remoteEntry.98ebff3d8d032c6d39d5.js
jupyterlab_wav/labextension/static/style.js
jupyterlab_wav/labextension/static/style_index_js.ab211c483152a20d7d37.js
jupyterlab_wav/labextension/static/style_index_js.ab211c483152a20d7d37.js.map
jupyterlab_wav/labextension/static/vendors-node_modules_colormap_index_js.8849ae701df12c76d0bd.js
jupyterlab_wav/labextension/static/vendors-node_modules_colormap_index_js.8849ae701df12c76d0bd.js.map
jupyterlab_wav/labextension/static/vendors-node_modules_css-loader_dist_runtime_api_js-node_modules_css-loader_dist_runtime_cssW-72eba1.12452d0f154828e4bd49.js
jupyterlab_wav/labextension/static/vendors-node_modules_css-loader_dist_runtime_api_js-node_modules_css-loader_dist_runtime_cssW-72eba1.12452d0f154828e4bd49.js.map
jupyterlab_wav/labextension/static/vendors-node_modules_wavesurfer_js_dist_plugin_wavesurfer_spectrogram_js-node_modules_wavesur-852146.a5af4683bdee618dad44.js
jupyterlab_wav/labextension/static/vendors-node_modules_wavesurfer_js_dist_plugin_wavesurfer_spectrogram_js-node_modules_wavesur-852146.a5af4683bdee618dad44.js.map
jupyterlab_wav-0.3.0.dist-info/LICENSE
jupyterlab_wav-0.3.0.dist-info/METADATA
jupyterlab_wav-0.3.0.dist-info/WHEEL
jupyterlab_wav-0.3.0.dist-info/top_level.txt
jupyterlab_wav-0.3.0.dist-info/RECORD
